MANIFEST.in
README.md
setup.py
osrframework_server/__init__.py
osrframework_server/server.py
osrframework_server.egg-info/PKG-INFO
osrframework_server.egg-info/SOURCES.txt
osrframework_server.egg-info/dependency_links.txt
osrframework_server.egg-info/entry_points.txt
osrframework_server.egg-info/requires.txt
osrframework_server.egg-info/top_level.txt
osrframework_server/config/server.cfg
osrframework_server/data/static/README.md
osrframework_server/data/static/composer.json
osrframework_server/data/static/favicon.ico
osrframework_server/data/static/license.txt
osrframework_server/data/static/css/explorify.css
osrframework_server/data/static/css/font-awesome.min.css
osrframework_server/data/static/css/jquery.fancybox-1.3.4.css
osrframework_server/data/static/css/keshif-style.css
osrframework_server/data/static/css/keshif.css
osrframework_server/data/static/css/kickstart-buttons.css
osrframework_server/data/static/css/kickstart-forms.css
osrframework_server/data/static/css/kickstart-grid.css
osrframework_server/data/static/css/kickstart-menus.css
osrframework_server/data/static/css/kickstart-slideshow.css
osrframework_server/data/static/css/kickstart-style.css
osrframework_server/data/static/css/kickstart.css
osrframework_server/data/static/css/prettify.css
osrframework_server/data/static/css/style.css
osrframework_server/data/static/css/tiptip.css
osrframework_server/data/static/css/fonts/font-awesome-4.2.0/css/font-awesome.css
osrframework_server/data/static/css/fonts/font-awesome-4.2.0/css/font-awesome.min.css
osrframework_server/data/static/css/fonts/font-awesome-4.2.0/fonts/FontAwesome.otf
osrframework_server/data/static/css/fonts/font-awesome-4.2.0/fonts/fontawesome-webfont.eot
osrframework_server/data/static/css/fonts/font-awesome-4.2.0/fonts/fontawesome-webfont.svg
osrframework_server/data/static/css/fonts/font-awesome-4.2.0/fonts/fontawesome-webfont.ttf
osrframework_server/data/static/css/fonts/font-awesome-4.2.0/fonts/fontawesome-webfont.woff
osrframework_server/data/static/css/fonts/font-awesome-4.2.0/less/bordered-pulled.less
osrframework_server/data/static/css/fonts/font-awesome-4.2.0/less/core.less
osrframework_server/data/static/css/fonts/font-awesome-4.2.0/less/fixed-width.less
