Metadata-Version: 1.1
Name: osrframework-server
Version: 0.18.0a4
Summary: OSRFramework Server - A HTTP server writen in Python to interact with OSRFramework.
Home-page: http://github.com/i3visio/osrframework_server
Author: Felix Brezo and Yaiza Rubio
Author-email: contacto@i3visio.com
License: COPYING
Keywords: python osint harvesting profiling maltego username socialmedia forums
Platform: UNKNOWN
Classifier: Development Status :: 4 - Beta
Classifier: Topic :: Software Development :: Libraries
Classifier: License :: OSI Approved :: GNU Affero General Public License v3 or later (AGPLv3+)
Classifier: Programming Language :: Python :: 2.7
Classifier: Intended Audience :: Developers
Classifier: Intended Audience :: Information Technology
Classifier: Intended Audience :: Science/Research
Classifier: Intended Audience :: Telecommunications Industry
Classifier: Topic :: Communications
Classifier: Topic :: Internet :: WWW/HTTP :: Indexing/Search
Classifier: Topic :: Scientific/Engineering :: Information Analysis
Classifier: Topic :: Scientific/Engineering :: Visualization
Classifier: Topic :: Text Processing :: Markup :: HTML
